tests/integration/__init__.py
tests/integration/asserts.py
tests/integration/conftest.py
tests/integration/test_integration_accounts.py
tests/integration/test_integration_activedocs.py
tests/integration/test_integration_api_client.py
tests/integration/test_integration_application.py
tests/integration/test_integration_application_plan.py
tests/integration/test_integration_backend_mapping_rules.py
tests/integration/test_integration_backend_metrics.py
tests/integration/test_integration_backend_usages.py
tests/integration/test_integration_backends.py
tests/integration/test_integration_custom_tenant.py
tests/integration/test_integration_limit.py
tests/integration/test_integration_mapping_rules.py
tests/integration/test_integration_methods.py
tests/integration/test_integration_metrics.py
tests/integration/test_integration_openapis.py
tests/integration/test_integration_policies.py
tests/integration/test_integration_policy_registry.py
tests/integration/test_integration_pricing_rules.py
tests/integration/test_integration_promotes.py
tests/integration/test_integration_services.py
threescale_api_crd/__init__.py
threescale_api_crd/client.py
threescale_api_crd/constants.py
threescale_api_crd/defaults.py
threescale_api_crd/resources.py
3scale_api_crd-0.1.6.dist-info/LICENSE
3scale_api_crd-0.1.6.dist-info/METADATA
3scale_api_crd-0.1.6.dist-info/WHEEL
3scale_api_crd-0.1.6.dist-info/top_level.txt
3scale_api_crd-0.1.6.dist-info/RECORD
