Metadata-Version: 2.1
Name: 3scale-api-crd
Version: 0.1.6
Summary: 3scale CRD Python Client
Home-page: https://github.com/3scale-qe/3scale-api-python-crd
Author: Martin Kudlej
Author-email: kudlej.martin@gmail.com
Maintainer: Matej Dujava
Maintainer-email: mdujava@redhat.com
Classifier: Programming Language :: Python :: 3
Classifier: Operating System :: OS Independent
Classifier: License :: OSI Approved :: Apache Software License
Classifier: Intended Audience :: Developers
Classifier: Topic :: Utilities
License-File: LICENSE
Requires-Dist: 3scale-api
Requires-Dist: openshift-client
Provides-Extra: dev
Requires-Dist: flake8; extra == "dev"
Requires-Dist: mypy; extra == "dev"
Requires-Dist: pylint; extra == "dev"
Requires-Dist: pytest; extra == "dev"
Requires-Dist: python-dotenv; extra == "dev"
Requires-Dist: backoff; extra == "dev"
Provides-Extra: docs
Requires-Dist: sphinx; extra == "docs"
